<emrtextdoc version="1.0" checkcount="0" senior=""><underwritemarks /><savelogs><savelog user_id="8228965" user_name="测医生" name="测医生" time="2017-11-30 14:21" ip="10.130.1.99" /></savelogs><docsetting modifytime="20171130142106" version="1.0" filename="C:\Users\Administrator\Desktop\1111.xml" title="" id="" defaultFontSize="12" defaultEnglishFontName="Times New Roman" defaultFontName="宋体" /><pagesetting paperwidth="827" paperheight="1169" leftmargin="79" topmargin="177" rightmargin="79" bottommargin="79" paperkind="A4" /><script runpwd="" editpwd=""><![CDATA[]]></script><text>患者姓名：曹杉杉
性别:女
年龄:33岁
住院号：17111041
疾病介绍和治疗建议
    医生已告知我患有或可疑疾病，需要在   麻醉下进行   检查/治疗。
其目的和预期效果是：2
    女性生殖器官活组织检查是自生殖器官病变处或可疑部位取小部分组织作病理学检查，简称活检。绝大多数活检可以作为诊断的最可靠依据。常用的检查/治疗有局部活组织检查（外阴、阴道、宫颈、子宫内膜）、宫颈Leep刀切除、宫颈息肉的摘除术、宫颈的物理治疗、经腹壁腹腔穿刺检查、经阴道后穹窿穿刺术。
手术潜在风险和对策
    医生告知我如下妇科检查/治疗可能发生的风险，有些不常见的风险可能没有在此列出，具体的手术式根据不同病人的情况有所不同，医生告诉我可与我的医生讨论有关我手术的具体内容，如果我有特殊的问题可与我的医生讨论。
1.我理解此手术可能发生的风险及医生的对策：
  1)术中出血；
  2)继发感染；
  3)因该操作是医生根据临床经验进行，因此，有可能所取组织没有取到病理改变部位，该检查仍然有漏诊可能；
  4)经腹壁腹腔穿刺检查、经阴道后穹窿穿刺术等可能会造成盆腹腔脏器如肠道损伤等。
2.我理解如果我患有高血压、心脏病、糖尿病、肝肾功能不全、静脉血栓等疾病或者有吸烟史，以上这些风险可能会加大。
特殊风险或主要高危因素
    我理解根据我个人的病情，我可能出现以下特殊并发症或风险：
                                                                                 一旦发生上述风险和意外，医生会采取积极应对措施。
患者知情选择
   ·我的医生已经告知我将要进行的检查/治疗方式、可能发生的并发症和风险、可能存在       的其它治疗方法并且解答了我关于此次检查/治疗的相关问题。
   ·我同意在检查/治疗中医生可以根据我的病情对预定的检查/治疗方式做出调整。
   ·我理解我的检查/治疗需要多位医生共同进行。
   ·我并未得到检查/治疗百分之百成功的许诺。
   ·我授权医师对检查/治疗涉及的病变器官、组织或标本进行处置，包括病理学检查、细       胞学检查和医疗废物处理等。
 
患者签名                                         签名日期      年   月   日
如果患者无法签署知情同意书，请其授权的亲属在此签名：
 
患者授权亲属签名           与患者关系            签名日期      年   月   日
医生陈述
    我已经告知患者将要进行的检查/治疗方式、此次检查/治疗及检查/治疗后可能发生的并发症和风险、可能存在的其它治疗方法并且解答了患者关于此次检查/治疗的相关问题。

医师签名                               签名日期      年   月   日

</text><head history_name="廊坊爱德堡医院" text_name="妇科检查/治疗知情同意书" section_id="8578994" bed_name="15" bed_id="8588076" section_name="妇产科" gender="1" sick_area="妇产科护理单元" /><body id="C5768B21325"><table id="C57F6031326" width="669"><row id="C57F6031327" width="660"><cell id="C57F6121328" width="183"><span operatercreater="0" forecolor="#000000">患者姓名：</span><input name="us_xm" operatercreater="0" forecolor="#000000"><span operatercreater="0">曹杉杉</span></input><p operatercreater="0" /></cell><cell id="C57F6121329" width="147"><span forecolor="#000000" operatercreater="0">性别:</span><input name="性别" operatercreater="0" forecolor="#000000"><span operatercreater="0">女</span></input><p operatercreater="0" /></cell><cell id="C57F6121330" width="157"><span forecolor="#000000" operatercreater="0">年龄:</span><input name="us_nl" operatercreater="0" forecolor="#000000"><span fontname="Times New Roman" operatercreater="0">33</span><span operatercreater="0">岁</span></input><p operatercreater="0" /></cell><cell id="C57F6121331" width="173"><span operatercreater="0" forecolor="#000000">住院号：</span><input name="住院号" operatercreater="0" forecolor="#000000"><span fontname="Times New Roman" operatercreater="0">17111041</span></input><p operatercreater="0" /></cell></row><row id="C57F6121332" width="660"><cell id="C57F6121333" width="660"><span fontbold="1" operatercreater="0" forecolor="#000000">疾病介绍和治疗建议</span><p operatercreater="0" /><span operatercreater="0" forecolor="#000000">    医生已告知我患有或可疑</span><input name="初步诊断" border-style="1" operatercreater="0" candelete="1" forecolor="#000000" /><span operatercreater="0" forecolor="#000000">疾病，需要在</span><input name="新增的输入域" border-style="1" operatercreater="0" forecolor="#000000"><span forecolor="#000000" operatercreater="0">   </span></input><span operatercreater="0" forecolor="#000000">麻醉下进行</span><input name="新增的输入域" border-style="1" operatercreater="0" forecolor="#000000"><span forecolor="#000000" operatercreater="0">   </span></input><span operatercreater="0" forecolor="#000000">检查/治疗。</span><p operatercreater="0" /><span operatercreater="0" forecolor="#000000">其目的和预期效果是：</span><span fontname="Times New Roman" operatercreater="0">2</span><p operatercreater="0" /><span operatercreater="0" forecolor="#000000">    女性生殖器官活组织检查是自生殖器官病变处或可疑部位取小部分组织作病理学检查，简称活检。绝大多数活检可以作为诊断的最可靠依据。常用的检查/治疗有局部活组织检查（外阴、阴道、宫颈、子宫内膜）、宫颈</span><span fontname="Times New Roman" operatercreater="0" forecolor="#000000">Leep</span><span operatercreater="0" forecolor="#000000">刀切除、宫颈息肉的摘除术、宫颈的物理治疗、经腹壁腹腔穿刺检查、经阴道后穹窿穿刺术。</span><p operatercreater="0" /></cell></row><row id="C57F6121337" width="660"><cell id="C57F6121338" width="660"><span fontbold="1" operatercreater="0" forecolor="#000000">手术潜在风险和对策</span><p operatercreater="0" /><span operatercreater="0" forecolor="#000000">    医生告知我如下妇科检查/治疗可能发生的风险，有些不常见的风险可能没有在此列出，具体的手术式根据不同病人的情况有所不同，医生告诉我可与我的医生讨论有关我手术的具体内容，如果我有特殊的问题可与我的医生讨论。</span><p operatercreater="0" /><span fontname="Times New Roman" operatercreater="0" forecolor="#000000">1</span><span operatercreater="0" forecolor="#000000">.我理解此手术可能发生的风险及医生的对策：</span><p operatercreater="0" /><span operatercreater="0" forecolor="#000000">  </span><span fontname="Times New Roman" operatercreater="0" forecolor="#000000">1</span><span operatercreater="0" forecolor="#000000">)术中出血；</span><p operatercreater="0" /><span operatercreater="0" forecolor="#000000">  </span><span fontname="Times New Roman" operatercreater="0" forecolor="#000000">2</span><span operatercreater="0" forecolor="#000000">)继发感染；</span><p operatercreater="0" /><span operatercreater="0" forecolor="#000000">  </span><span fontname="Times New Roman" operatercreater="0" forecolor="#000000">3</span><span operatercreater="0" forecolor="#000000">)因该操作是医生根据临床经验进行，因此，有可能所取组织没有取到病理改变部位，该检查仍然有漏诊可能；</span><p operatercreater="0" /><span operatercreater="0" forecolor="#000000">  </span><span fontname="Times New Roman" operatercreater="0" forecolor="#000000">4</span><span operatercreater="0" forecolor="#000000">)经腹壁腹腔穿刺检查、经阴道后穹窿穿刺术等可能会造成盆腹腔脏器如肠道损伤等。</span><p operatercreater="0" /><span fontname="Times New Roman" operatercreater="0" forecolor="#000000">2</span><span operatercreater="0" forecolor="#000000">.我理解如果我患有高血压、心脏病、糖尿病、肝肾功能不全、静脉血栓等疾病或者有吸烟史，以上这些风险可能会加大。</span><p operatercreater="0" /><span fontbold="1" operatercreater="0" forecolor="#000000">特殊风险或主要高危因素</span><p operatercreater="0" /><span operatercreater="0" forecolor="#000000">    我理解根据我个人的病情，我可能出现以下特殊并发症或风险：</span><p operatercreater="0" /><input name="新增的输入域" operatercreater="0" border-style="1" forecolor="#000000"><span operatercreater="0" forecolor="#000000">                                                                                 </span></input><span operatercreater="0" forecolor="#000000">一旦发生上述风险和意外，医生会采取积极应对措施。</span><p operatercreater="0" /></cell></row><row id="C57F6121342" width="660"><cell id="C57F6121343" width="660"><span fontbold="1" operatercreater="0" forecolor="#000000">患者知情选择</span><p operatercreater="0" /><span operatercreater="0" forecolor="#000000">   </span><span fontsize="16" operatercreater="0" forecolor="#000000">·</span><span operatercreater="0" forecolor="#000000">我的医生已经告知我将要进行的检查/治疗方式、可能发生的并发症和风险、可能存在       的其它治疗方法并且解答了我关于此次检查/治疗的相关问题。</span><p operatercreater="0" /><span operatercreater="0" forecolor="#000000">   </span><span fontsize="16" forecolor="#000000" operatercreater="0">·</span><span operatercreater="0" forecolor="#000000">我同意在检查/治疗中医生可以根据我的病情对预定的检查/治疗方式做出调整。</span><p operatercreater="0" /><span operatercreater="0" forecolor="#000000">   </span><span fontsize="16" forecolor="#000000" operatercreater="0">·</span><span operatercreater="0" forecolor="#000000">我理解我的检查/治疗需要多位医生共同进行。</span><p operatercreater="0" /><span operatercreater="0" forecolor="#000000">   </span><span fontsize="16" forecolor="#000000" operatercreater="0">·</span><span operatercreater="0" forecolor="#000000">我并未得到检查/治疗百分之百成功的许诺。</span><p operatercreater="0" /><span operatercreater="0" forecolor="#000000">   </span><span fontsize="16" forecolor="#000000" operatercreater="0">·</span><span operatercreater="0" forecolor="#000000">我授权医师对检查/治疗涉及的病变器官、组织或标本进行处置，包括病理学检查、细       胞学检查和医疗废物处理等。</span><p operatercreater="0" /><span forecolor="#000000" operatercreater="0"> </span><p operatercreater="0" /><span forecolor="#000000" operatercreater="0">患者签名</span><span forecolor="#000000" fontunderline="1" operatercreater="0">                                 </span><span forecolor="#000000" operatercreater="0">        签名日期</span><input name="日期" operatercreater="0" forecolor="#000000"><span forecolor="#000000" operatercreater="0">      年   月   日</span></input><p operatercreater="0" /><span forecolor="#000000" operatercreater="0">如果患者无法签署知情同意书，请其授权的亲属在此签名：</span><p operatercreater="0" /><span forecolor="#000000" operatercreater="0"> </span><p operatercreater="0" /><span forecolor="#000000" operatercreater="0">患者授权亲属签名</span><span forecolor="#000000" fontunderline="1" operatercreater="0">          </span><span forecolor="#000000" operatercreater="0"> 与患者关系</span><span forecolor="#000000" fontunderline="1" operatercreater="0">          </span><span forecolor="#000000" operatercreater="0">  签名日期</span><input name="日期" operatercreater="0" forecolor="#000000"><span forecolor="#000000" operatercreater="0">      年   月   日</span></input><p operatercreater="0" /></cell></row><row id="C57F6121347" width="660"><cell id="C57F6121348" width="660"><span fontbold="1" operatercreater="0" forecolor="#000000">医生陈述</span><p operatercreater="0" /><span operatercreater="0" forecolor="#000000">    我已经告知患者将要进行的检查/治疗方式、此次检查/治疗及检查/治疗后可能发生的并发症和风险、可能存在的其它治疗方法并且解答了患者关于此次检查/治疗的相关问题。</span><p operatercreater="0" /><p operatercreater="0" /><span forecolor="#000000" operatercreater="0">医师签名</span><input name="医师签名" operatercreater="0" forecolor="#000000"><span operatercreater="0" forecolor="#000000">     </span></input><span forecolor="#000000" operatercreater="0">                          签名日期</span><input name="日期" operatercreater="0" forecolor="#000000"><span forecolor="#000000" operatercreater="0">      年   月   日</span></input><p operatercreater="0" /></cell></row></table><p operatercreater="0" /></body></emrtextdoc>