<emrtextdoc version="1.0" checkcount="0" senior=""><underwritemarks /><savelogs><savelog user_id="8228965" user_name="测医生" name="测医生" time="2017-11-30 17:07" ip="10.130.1.99" /></savelogs><docsetting title="" id="" lineSpacing="15" paragraphSpacing="15" modifytime="20171130170809" version="1.0" defaultFontSize="12" defaultEnglishFontName="Times New Roman" defaultFontName="宋体" /><pagesetting paperwidth="827" paperheight="1169" leftmargin="98" topmargin="177" rightmargin="59" bottommargin="79" paperkind="A4" /><script runpwd="" editpwd=""><![CDATA[]]></script><text>患者：曹杉杉     单位或住址：
   患者主因“宫内孕13周，发热2天”入院。最高体温达39.4℃，物理降温及口服抗生素门诊治疗后效果欠佳，入院体温为38.8℃，入院后给予完善相关检查结果，抗生素静点抗炎、补液、雾化等其他对症治疗，向其交代若体温持续升高，有阴道出血、流产、难免流产等风险。患者及家属表示知情，理解。





患者及近亲属意见：


院方参加人员签字：

        测医生
</text><head history_name="廊坊爱德堡医院" text_name="谈   话   记   录" section_id="8578994" bed_name="15" bed_id="8588076" section_name="妇产科" gender="1" sick_area="妇产科护理单元" /><body id="CAC3B37E3"><span operatercreater="0" forecolor="#000000">患者：</span><input name="姓名" operatercreater="0" forecolor="#000000"><span operatercreater="0">曹杉杉</span></input><span operatercreater="0" forecolor="#000000">     单位或住址：</span><p operatercreater="0" /><hr operatercreater="0" forecolor="#000000" /><span operatercreater="0" forecolor="#000000">   患者主因“宫内孕</span><span fontname="Times New Roman" operatercreater="0" forecolor="#000000">13</span><span operatercreater="0" forecolor="#000000">周，发热</span><span fontname="Times New Roman" operatercreater="0" forecolor="#000000">2</span><span operatercreater="0" forecolor="#000000">天”入院。最高体温达</span><span fontname="Times New Roman" operatercreater="0" forecolor="#000000">39</span><span operatercreater="0" forecolor="#000000">.</span><span fontname="Times New Roman" operatercreater="0" forecolor="#000000">4</span><span operatercreater="0" forecolor="#000000">℃，物理降温及口服抗生素门诊治疗后效果欠佳，入院体温为</span><span fontname="Times New Roman" operatercreater="0" forecolor="#000000">38</span><span operatercreater="0" forecolor="#000000">.</span><span fontname="Times New Roman" operatercreater="0" forecolor="#000000">8</span><span operatercreater="0" forecolor="#000000">℃，入院后给予完善相关检查结果，抗生素静点抗炎、补液、雾化等其他对症治疗，向其交代若体温持续升高，有阴道出血、流产、难免流产等风险。患者及家属表示知情，理解。</span><p operatercreater="0" /><hr operatercreater="0" forecolor="#000000" /><table id="CAC6292A4" width="670" tableLock="1"><row id="CAC6292A5" width="660"><cell id="CAC6292A6" width="330" cell-style="border:;borderSlash:;linear:Solid"><p operatercreater="0" /></cell><cell id="CAC6292A8" width="330" cell-style="border:;borderSlash:;linear:Solid"><p operatercreater="0" /></cell></row><row id="CAC6292A10" width="660"><cell id="CAC6292A11" width="330" cell-style="border:;borderSlash:;linear:Solid"><p operatercreater="0" /></cell><cell id="CAC6292A13" width="330" cell-style="border:;borderSlash:;linear:Solid"><p operatercreater="0" /></cell></row><row id="CAC6292A15" width="660"><cell id="CAC6292A16" width="660" cell-style="border:;borderSlash:;linear:Solid"><p operatercreater="0" /></cell></row><row id="CAC6292A20" width="660"><cell id="CAC6292A21" width="660" cell-style="border:;borderSlash:;linear:Solid"><span operatercreater="0" forecolor="#000000">患者及近亲属意见：</span><p operatercreater="0" /><p operatercreater="0" /><p operatercreater="0" /></cell></row><row id="CAC903FE25" width="660"><cell id="CAC903FE26" width="660" cell-style="border:;borderSlash:;linear:Solid"><span operatercreater="0" forecolor="#000000">院方参加人员签字：</span><p operatercreater="0" /></cell></row></table><p operatercreater="0" /><input name="普通医师签名" sign="|2017-11-30 17:08签名从【】修改成【        测医生】" id="8228965" candelete="1" operatercreater="0"><span operatercreater="0">        测医生</span></input><input name="普通医师签名" sign="|2017-11-30 14:02签名从【】修改成【        刘静】" id="" candelete="1" operatercreater="0" forecolor="#000000" /><p operatercreater="0" align="1" /></body></emrtextdoc>