<emrtextdoc version="1.0" checkcount="0" senior=""><underwritemarks /><savelogs><savelog user_id="8228965" user_name="测医生" name="测医生" time="2017-12-05 15:47" ip="10.130.1.94" /></savelogs><docsetting modifytime="20171205154817" version="1.0" filename="C:\Documents and Settings\Administrator\桌面\00.xml" title="" id="" defaultFontSize="12" defaultEnglishFontName="Times New Roman" defaultFontName="宋体" /><pagesetting paperwidth="827" paperheight="1169" leftmargin="98" topmargin="177" rightmargin="59" bottommargin="79" paperkind="A4" /><script runpwd="" editpwd=""><![CDATA[]]></script><text>2017-12-05 15:47    2017-12-05 15:47

</text><head history_name="廊坊爱德堡医院" text_name="病   程   记   录" section_id="8578994" bed_name="15" bed_id="8588076" section_name="妇产科" gender="1" sick_area="妇产科护理单元" /><body id="C1523D179430"><div id="C8272494" marginLeft="10" candelete="1" timeTitle="Y" name="" title="2017-12-05 15:47   " hidetitle="1"><span fontbold="1" operatercreater="0">2017-12-05 15:47</span><p operatercreater="0" /></div><p operatercreater="0" /></body></emrtextdoc>