<emrtextdoc version="1.0" checkcount="0" senior=""><underwritemarks /><savelogs><savelog user_id="1000000000" user_name="管*****" name="管*****" time="2018-05-24 10:14" ip="fe80::cbd:3e0d:3f57:feaa%17" /></savelogs><docsetting modifytime="20180524101454" version="1.0" /><pagesetting paperwidth="827" paperheight="1169" leftmargin="98" topmargin="177" rightmargin="59" bottommargin="79" paperkind="A4" /><script runpwd="" editpwd=""><![CDATA[]]></script><text>
</text><head history_name="廊坊爱德堡医院" text_name="" /><body id="C58F99B1"><emrtextdoc version="1.0" checkcount="0" senior=""><underwritemarks /><savelogs><savelog user_id="1000000000" user_name="管理员" name="管理员" time="2017-07-27 09:04" ip="fe80::43:1c8c:2121:8f24%2" /></savelogs><docsetting modifytime="20170727113818" version="1.0" filename="E:\项目组\郑州人民医院\同意书xml模板\第十一章  儿科\抗胸腺细胞免疫球蛋白药物治疗知情同意书.xml" title="" id="" defaultFontSize="12" defaultEnglishFontName="Times New Roman" defaultFontName="宋体" /><pagesetting paperwidth="827" paperheight="1169" leftmargin="79" topmargin="177" rightmargin="79" bottommargin="79" paperkind="A4" /><script runpwd="" editpwd=""><![CDATA[]]></script><text>患者姓名：
性别:
年龄:
住院号：
疾病介绍和治疗建议
    该患儿为早产儿，目前还合并，于入住我科。正在我病房进行抢救，目前病情为：危   重   一般 （在相应情况前划“√”）。 
    我们将尽全力救治患儿，由于早产儿各脏器发育尚不完善，在诊治过程中可能会出现各个系统的病理变化，我们将进行密切监测，及时发现病情变化，积极救治。
    在住院期间，我们可能对患儿做的相应检查有：腰穿；胸穿；骨穿；侧脑室穿刺术；CT检查；脑干测听检查；超声心动检查等。
    救治患儿时，必要时可能需要应用：呼吸支持；机械通气；经外周静脉至中心静脉置管术；输血及血制品（包括白蛋白，丙种球蛋白，血浆等）；特殊用药如钙剂等；胸腔闭式引流术；侧脑室及硬膜下引流术；高级抗生素；静脉营养支持等治疗。
治疗潜在风险和对策
    医生告知我如下早产儿可能发生的风险，有些不常见的风险可能没有在此列出，具体的治疗根据不同病人的情况有所不同，医生告诉我可与我的医生讨论有关患儿治疗的具体内容，如果我有特殊的问题可与患儿的医生讨论。
    1.我理解任何麻醉都存在风险。
    2.我理解任何所用药物都可能产生副作用，包括轻度的恶心、皮疹等症状到严重的过敏性休克，甚至危及生命。
    3.我理解在监测、治疗过程中，可能发生的风险和医生的对策：
      1)体温调节功能不完善，患有硬肿症，可能出现肺出血，危及生命，采取暖箱保温措施；	
      2)呼吸系统发育不完善，患有呼吸暂停，呼吸窘迫综合征，肺出血，支气管肺发育不良。可能出现呼吸衰竭，呼吸机依赖，氧依赖，肺功能异常，危及生命。需采用呼吸机辅助通气；
      3)循环系统发育不完善，患有心功能不全，循环衰竭，持续胎儿循环，动脉导管未闭。可能出现心力衰竭，必要时可能需进行外科手术。采取强心，呼吸机辅助通气。		
      4)消化系统发育不完善，出现溢乳，呕吐，呛奶，腹泻，可能患有出血性坏死性小肠结肠炎，肠坏死，肠穿孔。采取部分或全胃肠外营养，必要时可能需进行外科手术
      5)神经系统发育不完善，患脑室周围白质软化，脑室及周围出血，脑室扩大。可能出现脑瘫，智力低下。需保静，止血，营养脑细胞治疗，必要时可能需进行外科手术。
      6)肝脏功能发育不完善，出现黄疸重，消退延迟，可能导致高胆红素血症，胆红素脑病，智力低下。需进行光疗，白蛋白输注，换血疗法。	
      7)肾脏及代谢功能发育不完善，出现酸碱失衡，电解质紊乱，并可能危及生命，需进行治疗保持内环境稳定。
      8)免疫系统发育不完善，可能并发各种感染，发生菌群失调，继发真菌感染。需使用抗生素，进行丙种球蛋白输注。
      9)皮肤、血管发育不完善，出现静脉输注液体外渗，局部皮肤、组织坏死，感染。需进行深静脉穿刺置管。
      10)视网膜发育不完善，发生晶体后纤维增生等，出现视力降低，失明。需定期检查，必要时手术。	
 
特殊风险或主要高危因素
    我理解根据患儿个人的病情，可能出现以下并发症或风险：
                                                                                 一旦发生上述风险和意外，医生会采取积极应对措施。 
患者知情选择
   ·我的医生已经告知我患儿将要进行的治疗方式、治疗及治疗后可能发生的并发症和风        险、可能存在的其它治疗方法并且解答了我关于此次治疗的相关问题。
   ·我同意在治疗中医生可以根据患儿的病情对预定的治疗方式做出调整。
   ·我理解患儿的治疗需要多位医生共同进行。
   ·我并未得到患儿治疗百分之百成功的许诺。
   ·我授权医师对治疗切除的病变器官、组织或标本进行处置，包括病理学检查、细胞学检     查和医疗废物处理等。
 
患者签名                                         签名日期      年   月   日
如果患者无法签署知情同意书，请其授权的亲属在此签名：
 
患者授权亲属签名           与患者关系            签名日期      年   月   日
医生陈述
    我已经告知患者将要进行的治疗方式、此次治疗及治疗后可能发生的并发症和风险、可能存在的其它治疗方法并且解答了患者关于此次治疗的相关问题。
  
医师签名                               签名日期      年   月   日

</text><head history_name="张家港市第三人民医院" text_name="" section_id="29" bed_name="35" bed_id="503968" section_name="北院关节创伤骨科" gender="0" sick_area="北院十六病室" /><body id="C5768B21325"><table id="C57F6031326" width="669" operatercreater="0"><row id="C57F6031327" width="660" operatercreater="0"><cell id="C57F6121328" width="183" operatercreater="0"><span operatercreater="0" forecolor="#000000">患者姓名：</span><input name="us_xm" operatercreater="0" forecolor="#000000" /><p operatercreater="0" /></cell><cell id="C57F6121329" width="147" operatercreater="0"><span forecolor="#000000" operatercreater="0">性别:</span><input name="性别" operatercreater="0" forecolor="#000000" /><p operatercreater="0" /></cell><cell id="C57F6121330" width="157" operatercreater="0"><span forecolor="#000000" operatercreater="0">年龄:</span><input name="us_nl" operatercreater="0" forecolor="#000000" /><p operatercreater="0" /></cell><cell id="C57F6121331" width="173" operatercreater="0"><span operatercreater="0" forecolor="#000000">住院号：</span><input name="住院号" operatercreater="0" forecolor="#000000" /><p operatercreater="0" /></cell></row><row id="C57F6121332" width="660" operatercreater="0"><cell id="C57F6121333" width="660" operatercreater="0"><span fontbold="1" operatercreater="0" forecolor="#000000">疾病介绍和治疗建议</span><p operatercreater="0" /><span operatercreater="0" forecolor="#000000">    该患儿为早产儿，目前还合并</span><input name="初步诊断" border-style="1" candelete="1" operatercreater="0" forecolor="#000000" /><span operatercreater="0" forecolor="#000000">，于</span><input name="us_rysj" operatercreater="0" forecolor="#000000" /><span operatercreater="0" forecolor="#000000">入住我科。正在我病房进行抢救，目前病情为：</span><checkbox check="N" operatercreater="0" forecolor="#000000" /><span operatercreater="0" forecolor="#000000">危   </span><checkbox check="N" operatercreater="0" forecolor="#000000" /><span operatercreater="0" forecolor="#000000">重   </span><checkbox check="N" operatercreater="0" forecolor="#000000" /><span operatercreater="0" forecolor="#000000">一般 （在相应情况前划“√”）。 </span><p operatercreater="0" /><span operatercreater="0" forecolor="#000000">    我们将尽全力救治患儿，由于早产儿各脏器发育尚不完善，在诊治过程中可能会出现各个系统的病理变化，我们将进行密切监测，及时发现病情变化，积极救治。</span><p operatercreater="0" /><span operatercreater="0" forecolor="#000000">    在住院期间，我们可能对患儿做的相应检查有：</span><checkbox check="N" operatercreater="0" forecolor="#000000" /><span operatercreater="0" forecolor="#000000">腰穿；</span><checkbox check="N" operatercreater="0" forecolor="#000000" /><span operatercreater="0" forecolor="#000000">胸穿；</span><checkbox check="N" operatercreater="0" forecolor="#000000" /><span operatercreater="0" forecolor="#000000">骨穿；</span><checkbox check="N" operatercreater="0" forecolor="#000000" /><span operatercreater="0" forecolor="#000000">侧脑室穿刺术；</span><checkbox check="N" operatercreater="0" forecolor="#000000" /><span fontname="Times New Roman" operatercreater="0" forecolor="#000000">CT</span><span operatercreater="0" forecolor="#000000">检查；</span><checkbox check="N" operatercreater="0" forecolor="#000000" /><span operatercreater="0" forecolor="#000000">脑干测听检查；</span><checkbox check="N" operatercreater="0" forecolor="#000000" /><span operatercreater="0" forecolor="#000000">超声心动检查等。</span><p operatercreater="0" /><span operatercreater="0" forecolor="#000000">    救治患儿时，必要时可能需要应用：</span><checkbox check="N" operatercreater="0" forecolor="#000000" /><span operatercreater="0" forecolor="#000000">呼吸支持；</span><checkbox check="N" operatercreater="0" forecolor="#000000" /><span operatercreater="0" forecolor="#000000">机械通气；</span><checkbox check="N" operatercreater="0" forecolor="#000000" /><span operatercreater="0" forecolor="#000000">经外周静脉至中心静脉置管术；</span><checkbox check="N" operatercreater="0" forecolor="#000000" /><span operatercreater="0" forecolor="#000000">输血及血制品（包括白蛋白，丙种球蛋白，血浆等）；</span><checkbox check="N" operatercreater="0" forecolor="#000000" /><span operatercreater="0" forecolor="#000000">特殊用药如钙剂等；</span><checkbox check="N" operatercreater="0" forecolor="#000000" /><span operatercreater="0" forecolor="#000000">胸腔闭式引流术；</span><checkbox check="N" operatercreater="0" forecolor="#000000" /><span operatercreater="0" forecolor="#000000">侧脑室及硬膜下引流术；</span><checkbox check="N" operatercreater="0" forecolor="#000000" /><span operatercreater="0" forecolor="#000000">高级抗生素；</span><checkbox check="N" operatercreater="0" forecolor="#000000" /><span operatercreater="0" forecolor="#000000">静脉营养支持等治疗。</span><p operatercreater="0" /></cell></row><row id="C57F6121337" width="660" operatercreater="0"><cell id="C57F6121338" width="660" operatercreater="0"><span fontbold="1" operatercreater="0" forecolor="#000000">治疗潜在风险和对策</span><p operatercreater="0" /><span operatercreater="0" forecolor="#000000">    医生告知我如下早产儿可能发生的风险，有些不常见的风险可能没有在此列出，具体的治疗根据不同病人的情况有所不同，医生告诉我可与我的医生讨论有关患儿治疗的具体内容，如果我有特殊的问题可与患儿的医生讨论。</span><p operatercreater="0" /><span operatercreater="0" forecolor="#000000">    </span><span fontname="Times New Roman" operatercreater="0" forecolor="#000000">1</span><span operatercreater="0" forecolor="#000000">.我理解任何麻醉都存在风险。</span><p operatercreater="0" /><span operatercreater="0" forecolor="#000000">    </span><span fontname="Times New Roman" operatercreater="0" forecolor="#000000">2</span><span operatercreater="0" forecolor="#000000">.我理解任何所用药物都可能产生副作用，包括轻度的恶心、皮疹等症状到严重的过敏性休克，甚至危及生命。</span><p operatercreater="0" /><span operatercreater="0" forecolor="#000000">    </span><span fontname="Times New Roman" operatercreater="0" forecolor="#000000">3</span><span operatercreater="0" forecolor="#000000">.我理解在监测、治疗过程中，可能发生的风险和医生的对策：</span><p operatercreater="0" /><span operatercreater="0" forecolor="#000000">      </span><span fontname="Times New Roman" operatercreater="0" forecolor="#000000">1</span><span operatercreater="0" forecolor="#000000">)体温调节功能不完善，患有硬肿症，可能出现肺出血，危及生命，采取暖箱保温措施；	</span><p operatercreater="0" /><span operatercreater="0" forecolor="#000000">      </span><span fontname="Times New Roman" operatercreater="0" forecolor="#000000">2</span><span operatercreater="0" forecolor="#000000">)呼吸系统发育不完善，患有呼吸暂停，呼吸窘迫综合征，肺出血，支气管肺发育不良。可能出现呼吸衰竭，呼吸机依赖，氧依赖，肺功能异常，危及生命。需采用呼吸机辅助通气；</span><p operatercreater="0" /><span operatercreater="0" forecolor="#000000">      </span><span fontname="Times New Roman" operatercreater="0" forecolor="#000000">3</span><span operatercreater="0" forecolor="#000000">)循环系统发育不完善，患有心功能不全，循环衰竭，持续胎儿循环，动脉导管未闭。可能出现心力衰竭，必要时可能需进行外科手术。采取强心，呼吸机辅助通气。		</span><p operatercreater="0" /><span operatercreater="0" forecolor="#000000">      </span><span fontname="Times New Roman" operatercreater="0" forecolor="#000000">4</span><span operatercreater="0" forecolor="#000000">)消化系统发育不完善，出现溢乳，呕吐，呛奶，腹泻，可能患有出血性坏死性小肠结肠炎，肠坏死，肠穿孔。采取部分或全胃肠外营养，必要时可能需进行外科手术</span><p operatercreater="0" /><span operatercreater="0" forecolor="#000000">      </span><span fontname="Times New Roman" operatercreater="0" forecolor="#000000">5</span><span operatercreater="0" forecolor="#000000">)神经系统发育不完善，患脑室周围白质软化，脑室及周围出血，脑室扩大。可能出现脑瘫，智力低下。需保静，止血，营养脑细胞治疗，必要时可能需进行外科手术。</span><p operatercreater="0" /><span operatercreater="0" forecolor="#000000">      </span><span fontname="Times New Roman" operatercreater="0" forecolor="#000000">6</span><span operatercreater="0" forecolor="#000000">)肝脏功能发育不完善，出现黄疸重，消退延迟，可能导致高胆红素血症，胆红素脑病，智力低下。需进行光疗，白蛋白输注，换血疗法。	</span><p operatercreater="0" /><span operatercreater="0" forecolor="#000000">      </span><span fontname="Times New Roman" operatercreater="0" forecolor="#000000">7</span><span operatercreater="0" forecolor="#000000">)肾脏及代谢功能发育不完善，出现酸碱失衡，电解质紊乱，并可能危及生命，需进行治疗保持内环境稳定。</span><p operatercreater="0" /><span operatercreater="0" forecolor="#000000">      </span><span fontname="Times New Roman" operatercreater="0" forecolor="#000000">8</span><span operatercreater="0" forecolor="#000000">)免疫系统发育不完善，可能并发各种感染，发生菌群失调，继发真菌感染。需使用抗生素，进行丙种球蛋白输注。</span><p operatercreater="0" /><span operatercreater="0" forecolor="#000000">      </span><span fontname="Times New Roman" operatercreater="0" forecolor="#000000">9</span><span operatercreater="0" forecolor="#000000">)皮肤、血管发育不完善，出现静脉输注液体外渗，局部皮肤、组织坏死，感染。需进行深静脉穿刺置管。</span><p operatercreater="0" /><span operatercreater="0" forecolor="#000000">      </span><span fontname="Times New Roman" operatercreater="0" forecolor="#000000">10</span><span operatercreater="0" forecolor="#000000">)视网膜发育不完善，发生晶体后纤维增生等，出现视力降低，失明。需定期检查，必要时手术。	</span><p operatercreater="0" /><span operatercreater="0" forecolor="#000000"> </span><p operatercreater="0" /><span fontbold="1" operatercreater="0" forecolor="#000000">特殊风险或主要高危因素</span><p operatercreater="0" /><span operatercreater="0" forecolor="#000000">    我理解根据患儿个人的病情，可能出现以下并发症或风险：</span><p operatercreater="0" /><input name="新增的输入域" operatercreater="0" border-style="1" forecolor="#000000"><span operatercreater="0" forecolor="#000000">                                                                                 </span></input><span operatercreater="0" forecolor="#000000">一旦发生上述风险和意外，医生会采取积极应对措施。 </span><p operatercreater="0" /></cell></row><row id="C57F6121342" width="660" operatercreater="0"><cell id="C57F6121343" width="660" operatercreater="0"><span fontbold="1" operatercreater="0" forecolor="#000000">患者知情选择</span><p operatercreater="0" /><span operatercreater="0" forecolor="#000000">   </span><span fontsize="16" operatercreater="0" forecolor="#000000">·</span><span operatercreater="0" forecolor="#000000">我的医生已经告知我患儿将要进行的治疗方式、治疗及治疗后可能发生的并发症和风        险、可能存在的其它治疗方法并且解答了我关于此次治疗的相关问题。</span><p operatercreater="0" /><span operatercreater="0" forecolor="#000000">   </span><span fontsize="16" forecolor="#000000" operatercreater="0">·</span><span operatercreater="0" forecolor="#000000">我同意在治疗中医生可以根据患儿的病情对预定的治疗方式做出调整。</span><p operatercreater="0" /><span operatercreater="0" forecolor="#000000">   </span><span fontsize="16" forecolor="#000000" operatercreater="0">·</span><span operatercreater="0" forecolor="#000000">我理解患儿的治疗需要多位医生共同进行。</span><p operatercreater="0" /><span operatercreater="0" forecolor="#000000">   </span><span fontsize="16" forecolor="#000000" operatercreater="0">·</span><span operatercreater="0" forecolor="#000000">我并未得到患儿治疗百分之百成功的许诺。</span><p operatercreater="0" /><span operatercreater="0" forecolor="#000000">   </span><span fontsize="16" forecolor="#000000" operatercreater="0">·</span><span operatercreater="0" forecolor="#000000">我授权医师对治疗切除的病变器官、组织或标本进行处置，包括病理学检查、细胞学检     查和医疗废物处理等。</span><p operatercreater="0" /><span forecolor="#000000" operatercreater="0"> </span><p operatercreater="0" /><span forecolor="#000000" operatercreater="0">患者签名</span><span forecolor="#000000" fontunderline="1" operatercreater="0">                                 </span><span forecolor="#000000" operatercreater="0">        签名日期</span><input name="日期" operatercreater="0" forecolor="#000000"><span forecolor="#000000" operatercreater="0">      年   月   日</span></input><p operatercreater="0" /><span forecolor="#000000" operatercreater="0">如果患者无法签署知情同意书，请其授权的亲属在此签名：</span><p operatercreater="0" /><span forecolor="#000000" operatercreater="0"> </span><p operatercreater="0" /><span forecolor="#000000" operatercreater="0">患者授权亲属签名</span><span forecolor="#000000" fontunderline="1" operatercreater="0">          </span><span forecolor="#000000" operatercreater="0"> 与患者关系</span><span forecolor="#000000" fontunderline="1" operatercreater="0">          </span><span forecolor="#000000" operatercreater="0">  签名日期</span><input name="日期" operatercreater="0" forecolor="#000000"><span forecolor="#000000" operatercreater="0">      年   月   日</span></input><p operatercreater="0" /></cell></row><row id="C57F6121347" width="660" operatercreater="0"><cell id="C57F6121348" width="660" operatercreater="0"><span fontbold="1" operatercreater="0" forecolor="#000000">医生陈述</span><p operatercreater="0" /><span operatercreater="0" forecolor="#000000">    我已经告知患者将要进行的治疗方式、此次治疗及治疗后可能发生的并发症和风险、可能存在的其它治疗方法并且解答了患者关于此次治疗的相关问题。</span><p operatercreater="0" /><span operatercreater="0" forecolor="#000000">  </span><p operatercreater="0" /><span forecolor="#000000" operatercreater="0">医师签名</span><input name="医师签名" operatercreater="0"><span operatercreater="0" forecolor="#000000">     </span></input><span forecolor="#000000" operatercreater="0">                          签名日期</span><input name="日期" operatercreater="0"><span forecolor="#000000" operatercreater="0">      年   月   日</span></input><p operatercreater="0" /></cell></row></table><p operatercreater="0" /></body></emrtextdoc></body></emrtextdoc>